nbdev_ignore/__init__.py
nbdev_ignore/_modidx.py
nbdev_ignore/core.py
nbdev_ignore-0.0.2.dist-info/LICENSE
nbdev_ignore-0.0.2.dist-info/METADATA
nbdev_ignore-0.0.2.dist-info/WHEEL
nbdev_ignore-0.0.2.dist-info/entry_points.txt
nbdev_ignore-0.0.2.dist-info/top_level.txt
nbdev_ignore-0.0.2.dist-info/RECORD
