Metadata-Version: 2.1
Name: nbdev-ignore
Version: 0.0.2
Summary: add an ignore directive to hide the cell and avoid execution during testing and docs generation in Jupyter notebooks when using nbdev for development.
Home-page: https://github.com/feynlee/nbdev-ignore
Author: Ziyue Li
Author-email: liziyue241@gmail.com
License: Apache Software License 2.0
Keywords: nbdev jupyter notebook python
Classifier: Development Status :: 4 - Beta
Classifier: Intended Audience :: Developers
Classifier: Natural Language :: English
Classifier: Programming Language :: Python :: 3.7
Classifier: Programming Language :: Python :: 3.8
Classifier: Programming Language :: Python :: 3.9
Classifier: Programming Language :: Python :: 3.10
Classifier: License :: OSI Approved :: Apache Software License
Requires-Python: >=3.7
License-File: LICENSE
Requires-Dist: nbdev
Provides-Extra: dev
